setup.py
frink/__init__.py
frink/base.py
frink/connection.py
frink/errors.py
frink/orm.py
frink/registry.py
frink/types.py
frink.egg-info/PKG-INFO
frink.egg-info/SOURCES.txt
frink.egg-info/dependency_links.txt
frink.egg-info/pbr.json
frink.egg-info/requires.txt
frink.egg-info/top_level.txt