Metadata-Version: 1.1
Name: frink
Version: 0.0.7
Summary: Basic ORM-like functionality for a RethinkDB datastore on top of Schematics.
Home-page: https://github.com/hactar-is/frink
Author: Hactar
Author-email: systems@hactar.is
License: UNKNOWN
Platform: UNKNOWN
Classifier: Development Status :: 2 - Pre-Alpha
Classifier: Programming Language :: Python
Classifier: Programming Language :: Python :: 2
Classifier: Programming Language :: Python :: 2.7
